bluetooth_sensor_state_data/__init__.py
bluetooth_sensor_state_data/py.typed
bluetooth_sensor_state_data-1.8.0.dist-info/LICENSE
bluetooth_sensor_state_data-1.8.0.dist-info/METADATA
bluetooth_sensor_state_data-1.8.0.dist-info/WHEEL
bluetooth_sensor_state_data-1.8.0.dist-info/RECORD
