Metadata-Version: 2.3
Name: bluetooth-sensor-state-data
Version: 1.8.0
Summary: Models for storing and converting Bluetooth Sensor State Data
License: Apache-2.0
Author: J. Nick Koston
Author-email: nick@koston.org
Requires-Python: >=3.11
Classifier: Development Status :: 2 - Pre-Alpha
Classifier: Intended Audience :: Developers
Classifier: License :: OSI Approved :: Apache Software License
Classifier: Natural Language :: English
Classifier: Operating System :: OS Independent
Classifier: Programming Language :: Python :: 3
Classifier: Programming Language :: Python :: 3.11
Classifier: Programming Language :: Python :: 3.12
Classifier: Programming Language :: Python :: 3.13
Classifier: Topic :: Software Development :: Libraries
Provides-Extra: docs
Requires-Dist: Sphinx (>=5,<8) ; extra == "docs"
Requires-Dist: bluetooth-data-tools (>=1.28.0)
Requires-Dist: habluetooth (>=3.42.0)
Requires-Dist: myst-parser (>=0.18,<3.1) ; extra == "docs"
Requires-Dist: sensor-state-data (>=2.0)
Requires-Dist: sphinx-rtd-theme (>=1,<4) ; extra == "docs"
Project-URL: Bug Tracker, https://github.com/bluetooth-devices/bluetooth-sensor-state-data/issues
Project-URL: Changelog, https://github.com/bluetooth-devices/bluetooth-sensor-state-data/blob/main/CHANGELOG.md
Project-URL: Documentation, https://bluetooth-sensor-state-data.readthedocs.io
Project-URL: Repository, https://github.com/bluetooth-devices/bluetooth-sensor-state-data
